README.md
setup.py
py2c2p/__init__.py
py2c2p.egg-info/PKG-INFO
py2c2p.egg-info/SOURCES.txt
py2c2p.egg-info/dependency_links.txt
py2c2p.egg-info/requires.txt
py2c2p.egg-info/top_level.txt