Metadata-Version: 2.1
Name: py2c2p
Version: 0.0.2
Summary: A Python library for 2c2p API
Home-page: https://github.com/sang-sakarin/py2c2p
Author: sang_sakarin
Author-email: sang_sakarin@outlook.com
License: sang_sakarin
Keywords: 2c2p 2c2p-python 2c2p-python-sdk
Platform: UNKNOWN
